nominally/__init__.py
nominally/__main__.py
nominally/api.py
nominally/config.py
nominally/parser.py
nominally/utilities.py
test/__init__.py
test/conftest.py
test/test__issues.py
test/test_api.py
test/test_cleaning.py
test/test_name_blasting.py
test/test_name_core.py
test/test_parse_ordering.py
test/test_prefix_conjunction.py
test/test_suffix_and_title.py
test/test_unbreakable.py
test/test_utilities.py
nominally-1.1.0.dist-info/LICENSE
nominally-1.1.0.dist-info/METADATA
nominally-1.1.0.dist-info/WHEEL
nominally-1.1.0.dist-info/entry_points.txt
nominally-1.1.0.dist-info/top_level.txt
nominally-1.1.0.dist-info/zip-safe
nominally-1.1.0.dist-info/RECORD
