Metadata-Version: 2.1
Name: nominally
Version: 1.1.0
Summary: A maximum-strength name parser for record linkage.
Home-page: https://github.com/vaneseltine/nominally
Author: Matt VanEseltine
Author-email: matvan@umich.edu
License: AGPL-3.0-or-later
Project-URL: Documentation, https://nominally.readthedocs.io/en/stable/
Project-URL: Examples, https://github.com/vaneseltine/nominally-examples/
Project-URL: Issue Tracker, https://github.com/vaneseltine/nominally/issues
Keywords: data,database,English,names,parser,text
Platform: UNKNOWN
Classifier: Development Status :: 5 - Production/Stable
Classifier: Environment :: Console
Classifier: Intended Audience :: Information Technology
Classifier: Intended Audience :: Science/Research
Classifier: License :: OSI Approved :: GNU Affero General Public License v3 or later (AGPLv3+)
Classifier: Natural Language :: English
Classifier: Programming Language :: Python
Classifier: Programming Language :: Python :: 3.7
Classifier: Programming Language :: Python :: 3.8
Classifier: Programming Language :: Python :: 3.9
Classifier: Programming Language :: Python :: 3.10
Classifier: Programming Language :: Python :: 3 :: Only
Classifier: Topic :: Database
Classifier: Topic :: Scientific/Engineering :: Information Analysis
Classifier: Topic :: Sociology
Classifier: Topic :: Text Processing :: Linguistic
Classifier: Typing :: Typed
Requires-Dist: unidecode (==1.2)
